PoreFinding/__init__.py
PoreFinding/download_files.py
PoreFinding/hole_analysis.py
PoreFinding/porefinding.py
PoreFinding/visualization.py
PoreFinding/ProbeParticleEllipsoid/ellipse_lib.py
PoreFinding/ProbeParticleEllipsoid/ellipsoid_optimisation.py
PoreFinding/hole2/hole
PoreFinding/hole2/sos_triangle
PoreFinding/hole2/sph_process
PoreFinding/pdb_models/7tu9.pdb
PoreFinding/pdb_models/7tu9.pdb_ellipsoid.pdb
PoreFinding/pdb_models/7tu9_aligned_z.pdb_pathway_ellipse.txt
PoreFinding/pdb_models/7tu9a_aligned_z.pdb
PoreFinding/pdb_models/7tu9a_aligned_z.sph
PoreFinding/pdb_models/7tvi.pdb
PoreFinding/pdb_models/8fe1.pdb
PoreFinding/tests/__init__.py
PoreFinding/tests/test_ellipse.py
PoreFinding/tests/test_ellipsoid_optimisation.py
PoreFinding/tests/test_hole.py
PoreFinding/tests/test_visualization.py
porefinding-0.0.3.dist-info/entry_points.txt
porefinding-0.0.3.dist-info/LICENSE
porefinding-0.0.3.dist-info/WHEEL
porefinding-0.0.3.dist-info/METADATA
porefinding-0.0.3.dist-info/RECORD
